[
null,
{"id":1,"list":[{"code":111,"indent":0,"parameters":[0,1,1]},{"code":121,"indent":1,"parameters":[1,1,0]},{"code":231,"indent":1,"parameters":[3,"CameraBack",1,0,384,216,100,100,50,0]},{"code":231,"indent":1,"parameters":[4,"CameraFront",1,0,384,216,100,100,50,0]},{"code":356,"indent":1,"parameters":["SetCustomCursor camera_cursor"]},{"code":0,"indent":1,"parameters":[]},{"code":411,"indent":0,"parameters":[]},{"code":356,"indent":1,"parameters":["ResetCustomCursor"]},{"code":235,"indent":1,"parameters":[3]},{"code":235,"indent":1,"parameters":[4]},{"code":121,"indent":1,"parameters":[1,1,1]},{"code":0,"indent":1,"parameters":[]},{"code":412,"indent":0,"parameters":[]},{"code":0,"indent":0,"parameters":[]}],"name":"polaroid_camera","switchId":1,"trigger":0},
{"id":2,"list":[{"code":112,"indent":0,"parameters":[]},{"code":234,"indent":1,"parameters":[3,[0,0,-68,0],40,true]},{"code":234,"indent":1,"parameters":[3,[0,0,0,0],40,true]},{"code":0,"indent":1,"parameters":[]},{"code":413,"indent":0,"parameters":[]},{"code":0,"indent":0,"parameters":[]}],"name":"polaroid_fading","switchId":1,"trigger":2},
{"id":3,"list":[{"code":0,"indent":0,"parameters":[]}],"name":"","switchId":1,"trigger":0},
{"id":4,"list":[{"code":0,"indent":0,"parameters":[]}],"name":"","switchId":1,"trigger":0},
{"id":5,"list":[{"code":0,"indent":0,"parameters":[]}],"name":"","switchId":1,"trigger":0},
{"id":6,"list":[{"code":111,"indent":0,"parameters":[1,6,0,0,0]},{"code":0,"indent":1,"parameters":[]},{"code":412,"indent":0,"parameters":[]},{"code":111,"indent":0,"parameters":[1,6,0,1,0]},{"code":0,"indent":1,"parameters":[]},{"code":412,"indent":0,"parameters":[]},{"code":111,"indent":0,"parameters":[1,6,0,2,0]},{"code":0,"indent":1,"parameters":[]},{"code":412,"indent":0,"parameters":[]},{"code":111,"indent":0,"parameters":[1,6,0,3,0]},{"code":0,"indent":1,"parameters":[]},{"code":412,"indent":0,"parameters":[]},{"code":0,"indent":0,"parameters":[]}],"name":"","switchId":1,"trigger":0},
{"id":7,"list":[{"code":0,"indent":0,"parameters":[]}],"name":"","switchId":1,"trigger":0},
{"id":8,"list":[{"code":0,"indent":0,"parameters":[]}],"name":"","switchId":1,"trigger":0},
{"id":9,"list":[{"code":0,"indent":0,"parameters":[]}],"name":"","switchId":1,"trigger":0},
{"id":10,"list":[{"code":0,"indent":0,"parameters":[]}],"name":"key_pieces","switchId":1,"trigger":0},
{"id":11,"list":[{"code":111,"indent":0,"parameters":[0,24,1]},{"code":101,"indent":1,"parameters":["",0,0,2]},{"code":401,"indent":1,"parameters":["flower quest initiated text"]},{"code":101,"indent":1,"parameters":["",0,0,2]},{"code":401,"indent":1,"parameters":["Get me red and blue flower"]},{"code":121,"indent":1,"parameters":[24,24,0]},{"code":0,"indent":1,"parameters":[]},{"code":411,"indent":0,"parameters":[]},{"code":101,"indent":1,"parameters":["",0,0,2]},{"code":401,"indent":1,"parameters":["Do you have what I asked for?"]},{"code":102,"indent":1,"parameters":[["Yes","No"],1,0,2,0]},{"code":402,"indent":1,"parameters":[0,"Yes"]},{"code":111,"indent":2,"parameters":[1,22,0,0,0]},{"code":111,"indent":3,"parameters":[12,"Check.each_is([23, 1],[24, 1],[25, 0],[26, 0],[27, 0])"]},{"code":122,"indent":4,"parameters":[23,27,0,0,0]},{"code":101,"indent":4,"parameters":["",0,0,2]},{"code":401,"indent":4,"parameters":["NO NO NO, I ASKED FOR TWO PURPLE FLOWERS TEXT"]},{"code":122,"indent":4,"parameters":[22,22,0,0,1]},{"code":0,"indent":4,"parameters":[]},{"code":411,"indent":3,"parameters":[]},{"code":122,"indent":4,"parameters":[23,27,0,0,0]},{"code":101,"indent":4,"parameters":["",0,0,2]},{"code":401,"indent":4,"parameters":["This is not what I asked for text"]},{"code":101,"indent":4,"parameters":["",0,0,2]},{"code":401,"indent":4,"parameters":["PLACEHOLDER PLAYERS FLOWERS GET ERASED, WHY? Text"]},{"code":101,"indent":4,"parameters":["",0,0,2]},{"code":401,"indent":4,"parameters":["Remember, I need red and blue text"]},{"code":0,"indent":4,"parameters":[]},{"code":412,"indent":3,"parameters":[]},{"code":0,"indent":3,"parameters":[]},{"code":411,"indent":2,"parameters":[]},{"code":111,"indent":3,"parameters":[1,22,0,1,0]},{"code":111,"indent":4,"parameters":[12,"Check.each_is([23, 0],[24, 0],[25, 0],[26, 2],[27, 0])"]},{"code":122,"indent":5,"parameters":[23,27,0,0,0]},{"code":101,"indent":5,"parameters":["",0,0,2]},{"code":401,"indent":5,"parameters":["THIS IS GREAT, NOW ANOTHER GREEN FLOWER text"]},{"code":401,"indent":5,"parameters":["rage of alex"]},{"code":122,"indent":5,"parameters":[22,22,0,0,2]},{"code":0,"indent":5,"parameters":[]},{"code":411,"indent":4,"parameters":[]},{"code":122,"indent":5,"parameters":[23,27,0,0,0]},{"code":101,"indent":5,"parameters":["",0,0,2]},{"code":401,"indent":5,"parameters":["This is not what I asked for text"]},{"code":101,"indent":5,"parameters":["",0,0,2]},{"code":401,"indent":5,"parameters":["PLACEHOLDER PLAYERS FLOWERS GET ERASED, WHY? Text"]},{"code":101,"indent":5,"parameters":["",0,0,2]},{"code":401,"indent":5,"parameters":["Remember, I need two purple, this is not it text"]},{"code":0,"indent":5,"parameters":[]},{"code":412,"indent":4,"parameters":[]},{"code":0,"indent":4,"parameters":[]},{"code":411,"indent":3,"parameters":[]},{"code":111,"indent":4,"parameters":[1,22,0,2,0]},{"code":111,"indent":5,"parameters":[12,"Check.each_is([23, 0],[24, 0],[25, 1],[26, 0],[27, 0])"]},{"code":122,"indent":6,"parameters":[23,27,0,0,0]},{"code":101,"indent":6,"parameters":["",0,0,2]},{"code":401,"indent":6,"parameters":["GREAT, YOU GOT THIS OLD TOKENS text"]},{"code":122,"indent":6,"parameters":[22,22,0,0,3]},{"code":121,"indent":6,"parameters":[23,23,1]},{"code":121,"indent":6,"parameters":[26,26,0]},{"code":0,"indent":6,"parameters":[]},{"code":411,"indent":5,"parameters":[]},{"code":122,"indent":6,"parameters":[23,27,0,0,0]},{"code":101,"indent":6,"parameters":["",0,0,2]},{"code":401,"indent":6,"parameters":["This is not what I asked for text"]},{"code":101,"indent":6,"parameters":["",0,0,2]},{"code":401,"indent":6,"parameters":["PLACEHOLDER PLAYERS FLOWERS GET ERASED, WHY? Text"]},{"code":101,"indent":6,"parameters":["",0,0,2]},{"code":401,"indent":6,"parameters":["Remember, I need a green one, this is not it text"]},{"code":0,"indent":6,"parameters":[]},{"code":412,"indent":5,"parameters":[]},{"code":0,"indent":5,"parameters":[]},{"code":412,"indent":4,"parameters":[]},{"code":0,"indent":4,"parameters":[]},{"code":412,"indent":3,"parameters":[]},{"code":0,"indent":3,"parameters":[]},{"code":412,"indent":2,"parameters":[]},{"code":0,"indent":2,"parameters":[]},{"code":402,"indent":1,"parameters":[1,"No"]},{"code":111,"indent":2,"parameters":[1,22,0,0,0]},{"code":101,"indent":3,"parameters":["",0,0,2]},{"code":401,"indent":3,"parameters":["Remember I need red and blue flower text"]},{"code":0,"indent":3,"parameters":[]},{"code":412,"indent":2,"parameters":[]},{"code":111,"indent":2,"parameters":[1,22,0,1,0]},{"code":101,"indent":3,"parameters":["",0,0,2]},{"code":401,"indent":3,"parameters":["Remember I need two purple flower text"]},{"code":0,"indent":3,"parameters":[]},{"code":412,"indent":2,"parameters":[]},{"code":111,"indent":2,"parameters":[1,22,0,2,0]},{"code":101,"indent":3,"parameters":["",0,0,2]},{"code":401,"indent":3,"parameters":["Remember I need a green flower text"]},{"code":0,"indent":3,"parameters":[]},{"code":412,"indent":2,"parameters":[]},{"code":0,"indent":2,"parameters":[]},{"code":404,"indent":1,"parameters":[]},{"code":0,"indent":1,"parameters":[]},{"code":412,"indent":0,"parameters":[]},{"code":0,"indent":0,"parameters":[]}],"name":"flowerQ","switchId":1,"trigger":0},
{"id":12,"list":[{"code":111,"indent":0,"parameters":[1,28,0,0,0]},{"code":101,"indent":1,"parameters":["",0,0,2]},{"code":401,"indent":1,"parameters":["i'm a cat"]},{"code":122,"indent":1,"parameters":[28,28,0,0,1]},{"code":111,"indent":1,"parameters":[1,28,0,1,0]},{"code":101,"indent":2,"parameters":["",0,0,2]},{"code":401,"indent":2,"parameters":["meow"]},{"code":122,"indent":2,"parameters":[28,28,0,0,2]},{"code":0,"indent":2,"parameters":[]},{"code":412,"indent":1,"parameters":[]},{"code":101,"indent":1,"parameters":["",0,0,2]},{"code":401,"indent":1,"parameters":["..."]},{"code":0,"indent":1,"parameters":[]},{"code":412,"indent":0,"parameters":[]},{"code":0,"indent":0,"parameters":[]}],"name":"rager_cat","switchId":1,"trigger":0},
{"id":13,"list":[{"code":111,"indent":0,"parameters":[0,29,1]},{"code":121,"indent":1,"parameters":[29,29,0]},{"code":231,"indent":1,"parameters":[1,"MapPSDBack",1,0,384,216,100,100,180,0]},{"code":231,"indent":1,"parameters":[2,"MapPSDFront",1,0,384,216,100,100,255,0]},{"code":0,"indent":1,"parameters":[]},{"code":411,"indent":0,"parameters":[]},{"code":117,"indent":1,"parameters":[15]},{"code":0,"indent":1,"parameters":[]},{"code":412,"indent":0,"parameters":[]},{"code":0,"indent":0,"parameters":[]}],"name":"rager_minimap","switchId":29,"trigger":0},
{"id":14,"list":[{"code":112,"indent":0,"parameters":[]},{"code":234,"indent":1,"parameters":[2,[0,-85,0,0],40,true]},{"code":234,"indent":1,"parameters":[2,[0,68,0,0],80,true]},{"code":0,"indent":1,"parameters":[]},{"code":413,"indent":0,"parameters":[]},{"code":0,"indent":0,"parameters":[]}],"name":"rager_minimap_fading","switchId":29,"trigger":2},
{"id":15,"list":[{"code":235,"indent":0,"parameters":[1]},{"code":235,"indent":0,"parameters":[2]},{"code":121,"indent":0,"parameters":[29,29,1]},{"code":0,"indent":0,"parameters":[]}],"name":"rager_minimap_close","switchId":29,"trigger":0},
{"id":16,"list":[{"code":0,"indent":0,"parameters":[]}],"name":"","switchId":1,"trigger":0},
{"id":17,"list":[{"code":0,"indent":0,"parameters":[]}],"name":"","switchId":1,"trigger":0},
{"id":18,"list":[{"code":0,"indent":0,"parameters":[]}],"name":"","switchId":1,"trigger":0},
{"id":19,"list":[{"code":0,"indent":0,"parameters":[]}],"name":"","switchId":1,"trigger":0},
{"id":20,"list":[{"code":0,"indent":0,"parameters":[]}],"name":"","switchId":1,"trigger":0},
{"id":21,"list":[{"code":0,"indent":0,"parameters":[]}],"name":"","switchId":1,"trigger":0},
{"id":22,"list":[{"code":0,"indent":0,"parameters":[]}],"name":"","switchId":1,"trigger":0},
{"id":23,"list":[{"code":0,"indent":0,"parameters":[]}],"name":"","switchId":1,"trigger":0},
{"id":24,"list":[{"code":0,"indent":0,"parameters":[]}],"name":"","switchId":1,"trigger":0},
{"id":25,"list":[{"code":0,"indent":0,"parameters":[]}],"name":"","switchId":1,"trigger":0},
{"id":26,"list":[{"code":0,"indent":0,"parameters":[]}],"name":"","switchId":1,"trigger":0},
{"id":27,"list":[{"code":0,"indent":0,"parameters":[]}],"name":"","switchId":1,"trigger":0},
{"id":28,"list":[{"code":0,"indent":0,"parameters":[]}],"name":"","switchId":1,"trigger":0},
{"id":29,"list":[{"code":0,"indent":0,"parameters":[]}],"name":"","switchId":1,"trigger":0},
{"id":30,"list":[{"code":0,"indent":0,"parameters":[]}],"name":"","switchId":1,"trigger":0},
{"id":31,"list":[{"code":0,"indent":0,"parameters":[]}],"name":"","switchId":1,"trigger":0},
{"id":32,"list":[{"code":0,"indent":0,"parameters":[]}],"name":"","switchId":1,"trigger":0},
{"id":33,"list":[{"code":0,"indent":0,"parameters":[]}],"name":"","switchId":1,"trigger":0},
{"id":34,"list":[{"code":0,"indent":0,"parameters":[]}],"name":"","switchId":1,"trigger":0},
{"id":35,"list":[{"code":0,"indent":0,"parameters":[]}],"name":"","switchId":1,"trigger":0},
{"id":36,"list":[{"code":0,"indent":0,"parameters":[]}],"name":"","switchId":1,"trigger":0},
{"id":37,"list":[{"code":0,"indent":0,"parameters":[]}],"name":"","switchId":1,"trigger":0},
{"id":38,"list":[{"code":0,"indent":0,"parameters":[]}],"name":"","switchId":1,"trigger":0},
{"id":39,"list":[{"code":0,"indent":0,"parameters":[]}],"name":"","switchId":1,"trigger":0},
{"id":40,"list":[{"code":0,"indent":0,"parameters":[]}],"name":"","switchId":1,"trigger":0},
{"id":41,"list":[{"code":0,"indent":0,"parameters":[]}],"name":"","switchId":1,"trigger":0},
{"id":42,"list":[{"code":0,"indent":0,"parameters":[]}],"name":"","switchId":1,"trigger":0},
{"id":43,"list":[{"code":0,"indent":0,"parameters":[]}],"name":"","switchId":1,"trigger":0},
{"id":44,"list":[{"code":0,"indent":0,"parameters":[]}],"name":"","switchId":1,"trigger":0},
{"id":45,"list":[{"code":0,"indent":0,"parameters":[]}],"name":"","switchId":1,"trigger":0},
{"id":46,"list":[{"code":0,"indent":0,"parameters":[]}],"name":"","switchId":1,"trigger":0},
{"id":47,"list":[{"code":0,"indent":0,"parameters":[]}],"name":"","switchId":1,"trigger":0},
{"id":48,"list":[{"code":0,"indent":0,"parameters":[]}],"name":"","switchId":1,"trigger":0},
{"id":49,"list":[{"code":0,"indent":0,"parameters":[]}],"name":"","switchId":1,"trigger":0},
{"id":50,"list":[{"code":0,"indent":0,"parameters":[]}],"name":"","switchId":1,"trigger":0}
]